alexandria_upload.py
Alexandria_Upload_Utils-0.1.2.dist-info/pydist.json
Alexandria_Upload_Utils-0.1.2.dist-info/WHEEL
Alexandria_Upload_Utils-0.1.2.dist-info/METADATA
Alexandria_Upload_Utils-0.1.2.dist-info/DESCRIPTION.rst
Alexandria_Upload_Utils-0.1.2.dist-info/top_level.txt
Alexandria_Upload_Utils-0.1.2.dist-info/RECORD
