Metadata-Version: 2.0
Name: Alexandria-Upload-Utils
Version: 0.1.2
Summary: Easy uploads to an Alexandria build archive
Home-page: https://github.com/tedw4rd/alexandria-upload-utils/
Author: Ted Aronson
Author-email: ted.aronson@gmail.com
License: MIT
Platform: any
Classifier: Development Status :: 4 - Beta
Classifier: Environment :: Console
Classifier: Intended Audience :: Developers
Classifier: License :: OSI Approved :: MIT License
Classifier: Operating System :: OS Independent
Classifier: Programming Language :: Python
Classifier: Topic :: Internet :: WWW/HTTP :: Dynamic Content
Classifier: Topic :: Software Development :: Libraries :: Python Modules
Requires-Dist: requests (>=2.0.0)
